pydev_cli/__init__.py
pydev_cli/cli.py
pydev_cli/config.py
pydev_cli/utils.py
pydev_cli-2.0.0.dist-info/entry_points.txt
pydev_cli-2.0.0.dist-info/WHEEL
pydev_cli-2.0.0.dist-info/METADATA
pydev_cli-2.0.0.dist-info/RECORD
